[
  {
    "StopID": "29",
    "timestamp": "2019-10-16T11:58:17.831Z",
    "Direction": "Inbound",
    "Destination": "Broombridge",
    "Time": "00:03:49",
    "AVLS": "00:04:29",
    "Tram": "5005",
    "Action": "a",
    "Msg Sent": "16/10/2019 12:58:12",
    "Msg Received": "16/10/2019 12:58:12",
    "Msg Processed": "16/10/2019 12:58:13",
    "XML ID": "16900",
    "Total Lag": "1.0615892",
    "Create Lag": "0.575829",
    "Process Lag": "0.4857602"
  },
  {
    "StopID": "29",
    "timestamp": "2019-10-16T11:58:17.831Z",
    "Direction": "Inbound",
    "Destination": "Parnell",
    "Time": "00:09:07",
    "AVLS": "00:09:47",
    "Tram": "5023",
    "Action": "a",
    "Msg Sent": "16/10/2019 12:58:14",
    "Msg Received": "16/10/2019 12:58:15",
    "Msg Processed": "16/10/2019 12:58:15",
    "XML ID": "16901",
    "Total Lag": "1.4682964",
    "Create Lag": "1.3740861",
    "Process Lag": "0.0942103"
  },
  {
    "StopID": "29",
    "timestamp": "2019-10-16T11:58:17.831Z",
    "Direction": "Inbound",
    "Destination": "Broombridge",
    "Time": "00:14:40",
    "AVLS": "00:15:20",
    "Tram": "5006",
    "Action": "a",
    "Msg Sent": "16/10/2019 12:58:12",
    "Msg Received": "16/10/2019 12:58:12",
    "Msg Processed": "16/10/2019 12:58:13",
    "XML ID": "16900",
    "Total Lag": "1.1084654",
    "Create Lag": "0.575829",
    "Process Lag": "0.5326364"
  },
  {
    "StopID": "29",
    "timestamp": "2019-10-16T11:58:17.831Z",
    "Direction": "Outbound",
    "Destination": "Sandyford",
    "Time": "00:00:00",
    "AVLS": "00:00:00",
    "Tram": "5029",
    "Action": "a",
    "Msg Sent": "16/10/2019 12:58:01",
    "Msg Received": "16/10/2019 12:58:01",
    "Msg Processed": "16/10/2019 12:58:01",
    "XML ID": "16892",
    "Total Lag": "0.1226248",
    "Create Lag": "0.1226248",
    "Process Lag": "0"
  },
  {
    "StopID": "29",
    "timestamp": "2019-10-16T11:58:17.831Z",
    "Direction": "Outbound",
    "Destination": "Bride's Glen",
    "Time": "00:04:10",
    "AVLS": "00:04:50",
    "Tram": "5022",
    "Action": "a",
    "Msg Sent": "16/10/2019 12:58:14",
    "Msg Received": "16/10/2019 12:58:15",
    "Msg Processed": "16/10/2019 12:58:15",
    "XML ID": "16901",
    "Total Lag": "1.641192",
    "Create Lag": "1.3740861",
    "Process Lag": "0.2671059"
  },
  {
    "StopID": "29",
    "timestamp": "2019-10-16T11:58:17.831Z",
    "Direction": "Outbound",
    "Destination": "Sandyford",
    "Time": "00:10:37",
    "AVLS": "00:11:17",
    "Tram": "5028",
    "Action": "a",
    "Msg Sent": "16/10/2019 12:58:14",
    "Msg Received": "16/10/2019 12:58:15",
    "Msg Processed": "16/10/2019 12:58:15",
    "XML ID": "16901",
    "Total Lag": "1.5625519",
    "Create Lag": "1.3740861",
    "Process Lag": "0.1884658"
  }
]